md4c/__init__.py
md4c/abc.py
md4c/binds.py
md4c/clients.py
md4c/details.py
md4c/enums.py
md4c/flags.py
md4c/helpers.py
md4c/parsers.py
md4c/protos.py
md4c/types.py
md4c/wraps.py
md4c-1.0.0.dist-info/LICENCE
md4c-1.0.0.dist-info/METADATA
md4c-1.0.0.dist-info/WHEEL
md4c-1.0.0.dist-info/top_level.txt
md4c-1.0.0.dist-info/RECORD
