Metadata-Version: 2.1
Name: md4c
Version: 1.0.0
Summary: Markdown parsing.
Home-page: https://github.com/Exahilosys/md4c
Author: Exahilosys
License: MIT
Platform: UNKNOWN
Provides-Extra: ansi
Requires-Dist: sty ; extra == 'ansi'
Provides-Extra: html
Requires-Dist: bs4 ; extra == 'html'
